MANIFEST.in
README.rst
setup.py
docs/HISTORY.txt
docs/candlestick.jpg
ftw/__init__.py
ftw.candlestick.egg-info/PKG-INFO
ftw.candlestick.egg-info/SOURCES.txt
ftw.candlestick.egg-info/dependency_links.txt
ftw.candlestick.egg-info/entry_points.txt
ftw.candlestick.egg-info/namespace_packages.txt
ftw.candlestick.egg-info/not-zip-safe
ftw.candlestick.egg-info/requires.txt
ftw.candlestick.egg-info/top_level.txt
ftw/candlestick/__init__.py
ftw/candlestick/configure.zcml
ftw/candlestick/testing.py
ftw/candlestick/Extensions/__init__.py
ftw/candlestick/Extensions/install.py
ftw/candlestick/js/src/DOMParser.js
ftw/candlestick/js/src/ftw.candlestick.js
ftw/candlestick/js/src/phonevalidator.js
ftw/candlestick/js/test/fixtures/complex_numbers.html
ftw/candlestick/js/test/fixtures/iban_number.html
ftw/candlestick/js/test/fixtures/integration.html
ftw/candlestick/js/test/fixtures/parentheses.html
ftw/candlestick/js/test/fixtures/phonenumbers.js
ftw/candlestick/js/test/fixtures/short_number.html
ftw/candlestick/js/test/fixtures/simple_numbers.html
ftw/candlestick/js/test/fixtures/spaced_numbers.html
ftw/candlestick/js/test/fixtures/text_nodes.html
ftw/candlestick/js/test/fixtures/trailing_text.html
ftw/candlestick/js/test/helpers/elements.js
ftw/candlestick/js/test/helpers/string.js
ftw/candlestick/js/test/spec/DOMParser.js
ftw/candlestick/js/test/spec/integration.js
ftw/candlestick/js/test/spec/phonevalidator.js
ftw/candlestick/profiles/default/jsregistry.xml
ftw/candlestick/profiles/default/metadata.xml
ftw/candlestick/profiles/default_plone5/metadata.xml
ftw/candlestick/profiles/default_plone5/registry.xml
ftw/candlestick/profiles/uninstall/jsregistry.xml
ftw/candlestick/profiles/uninstall_plone5/metadata.xml
ftw/candlestick/profiles/uninstall_plone5/registry.xml
ftw/candlestick/resources/candlestick-compiled.js
ftw/candlestick/resources/candlestick.integration.js
ftw/candlestick/resources/ftw.candlestick.js
ftw/candlestick/resources/main.js
ftw/candlestick/tests/__init__.py
ftw/candlestick/tests/test_profiles.py
ftw/candlestick/tests/test_uninstall.py
ftw/candlestick/upgrades/__init__.py
ftw/candlestick/upgrades/20191212090031_fix_plone_5_profile/__init__.py
ftw/candlestick/upgrades/20191212090031_fix_plone_5_profile/registry.xml
